napari_locpix/__init__.py
napari_locpix/_datastruc.py
napari_locpix/_sample_data.py
napari_locpix/_widget.py
napari_locpix/napari.yaml
napari_locpix/_tests/__init__.py
napari_locpix/_tests/test_sample_data.py
napari_locpix/_tests/test_widget.py
napari_locpix-0.0.6.dist-info/LICENSE
napari_locpix-0.0.6.dist-info/METADATA
napari_locpix-0.0.6.dist-info/WHEEL
napari_locpix-0.0.6.dist-info/entry_points.txt
napari_locpix-0.0.6.dist-info/top_level.txt
napari_locpix-0.0.6.dist-info/RECORD
