Metadata-Version: 2.1
Name: napari-locpix
Version: 0.0.6
Summary: Load in SMLM data and annotate within napari
Home-page: https://github.com/oubino/napari-locpix
Author: Oliver Umney
Author-email: scou@leeds.ac.uk
License: MIT
Project-URL: Bug Tracker, https://github.com/oubino/napari-locpix/issues
Project-URL: Documentation, https://github.com/oubino/napari-locpix#README.md
Project-URL: Source Code, https://github.com/oubino/napari-locpix
Project-URL: User Support, https://github.com/oubino/napari-locpix/issues
Classifier: Development Status :: 2 - Pre-Alpha
Classifier: Framework :: napari
Classifier: Intended Audience :: Developers
Classifier: License :: OSI Approved :: MIT License
Classifier: Operating System :: OS Independent
Classifier: Programming Language :: Python
Classifier: Programming Language :: Python :: 3
Classifier: Programming Language :: Python :: 3 :: Only
Classifier: Programming Language :: Python :: 3.8
Classifier: Programming Language :: Python :: 3.9
Classifier: Programming Language :: Python :: 3.10
Classifier: Topic :: Scientific/Engineering :: Image Processing
Requires-Python: >=3.8
License-File: LICENSE
Requires-Dist: numpy
Requires-Dist: qtpy
Requires-Dist: polars
Requires-Dist: pyarrow
Provides-Extra: testing
Requires-Dist: tox ; extra == 'testing'
Requires-Dist: pytest ; extra == 'testing'
Requires-Dist: pytest-cov ; extra == 'testing'
Requires-Dist: pytest-qt ; extra == 'testing'
Requires-Dist: napari ; extra == 'testing'
Requires-Dist: pyqt5 ; extra == 'testing'
